main.py
utils/__init__.py
utils/colors.py
utils/create_world.py
utils/utils.py
utils/view_worlds.py
worlds_creator-0.1.0.dist-info/LICENSE
worlds_creator-0.1.0.dist-info/METADATA
worlds_creator-0.1.0.dist-info/WHEEL
worlds_creator-0.1.0.dist-info/entry_points.txt
worlds_creator-0.1.0.dist-info/top_level.txt
worlds_creator-0.1.0.dist-info/RECORD
