Metadata-Version: 2.1
Name: worlds_creator
Version: 0.1.0
Summary: A package to create and view worlds.
Home-page: https://github.com/sun2ii/worlds
Author: Your Name
Author-email: benbasuni1@gmail.com
License: MIT
Classifier: Programming Language :: Python :: 3
Classifier: License :: OSI Approved :: MIT License
Classifier: Operating System :: OS Independent
Requires-Python: >=3.6
License-File: LICENSE
